dbt_cloud_api_client/__init__.py
dbt_cloud_api_client/account.py
dbt_cloud_api_client/base.py
dbt_cloud_api_client/client.py
dbt_cloud_api_client/job.py
dbt_cloud_api_client/run.py
dbt_cloud_api_client-0.0.1.dist-info/LICENSE
dbt_cloud_api_client-0.0.1.dist-info/METADATA
dbt_cloud_api_client-0.0.1.dist-info/WHEEL
dbt_cloud_api_client-0.0.1.dist-info/top_level.txt
dbt_cloud_api_client-0.0.1.dist-info/RECORD
