Metadata-Version: 2.1
Name: dbt-cloud-api-client
Version: 0.0.1
Summary: DBT Cloud API client
Home-page: https://github.com/triedandtested-dev/dbt_cloud_api_client
Author: Tried and Tested
Author-email: bryan@triedandtested.dev
License: UNKNOWN
Project-URL: Bug Tracker, https://github.com/triedandtested-dev/dbt_cloud_api_client/issues
Platform: UNKNOWN
Classifier: Programming Language :: Python :: 3
Classifier: Operating System :: OS Independent
Requires-Python: >=3.6
License-File: LICENSE
